README.md
setup.py
creativity/__init__.py
creativity.egg-info/PKG-INFO
creativity.egg-info/SOURCES.txt
creativity.egg-info/dependency_links.txt
creativity.egg-info/requires.txt
creativity.egg-info/top_level.txt