Metadata-Version: 2.1
Name: creativity
Version: 1.1.5
Summary: Quick inspiration
Home-page: https://github.com/ajaska/creativity
Author: Arlan Jaska
Author-email: akjaska@gmail.com
License: UNKNOWN
Platform: UNKNOWN
Classifier: Programming Language :: Python :: 3
Classifier: License :: OSI Approved :: MIT License
Classifier: Operating System :: OS Independent
Classifier: Topic :: Artistic Software
